jsbgym/__init__.py
jsbgym/aircraft.py
jsbgym/assessors.py
jsbgym/basic_ic.xml
jsbgym/environment.py
jsbgym/flightgear.xml
jsbgym/minimal_ic.xml
jsbgym/properties.py
jsbgym/rewards.py
jsbgym/simulation.py
jsbgym/tasks.py
jsbgym/utils.py
jsbgym/visualiser.py
jsbgym/agents/__init__.py
jsbgym/agents/agents.py
jsbgym/tests/__init__.py
jsbgym/tests/manual_tests.py
jsbgym/tests/stubs.py
jsbgym/tests/test_agents.py
jsbgym/tests/test_assessors.py
jsbgym/tests/test_environment.py
jsbgym/tests/test_functional.py
jsbgym/tests/test_geodetic_position.py
jsbgym/tests/test_rewards.py
jsbgym/tests/test_simulation.py
jsbgym/tests/test_tasks.py
jsbgym/tests/test_visualiser.py
jsbgym-0.4.0.dist-info/LICENSE
jsbgym-0.4.0.dist-info/METADATA
jsbgym-0.4.0.dist-info/WHEEL
jsbgym-0.4.0.dist-info/top_level.txt
jsbgym-0.4.0.dist-info/RECORD
