Metadata-Version: 2.1
Name: jsbgym
Version: 0.4.0
Summary: A package of reinforcement learning environments for flight control using the JSBSim flight dynamics model.
Author: sryu1
License: MIT
Project-URL: Homepage, https://github.com/sryu1/jsbgym
Project-URL: Repository, https://github.com/sryu1/jsbgym
Project-URL: Bug Tracker, https://github.com/sryu1/jsbgym/issues
Classifier: License :: OSI Approved :: MIT License
Classifier: Programming Language :: Python :: 3.8
Classifier: Programming Language :: Python :: 3.9
Classifier: Programming Language :: Python :: 3.10
Classifier: Programming Language :: Python :: 3.11
Classifier: Programming Language :: Python :: 3.12
Classifier: Topic :: Scientific/Engineering :: Artificial Intelligence
Requires-Python: >=3.8
License-File: LICENSE
Requires-Dist: numpy
Requires-Dist: gymnasium
Requires-Dist: jsbsim
Requires-Dist: matplotlib
